{"images":[
{"index": "90", "name": "img (79).jpg", "width": "367", "height": "239"},
{"index": "91", "name": "img (8).jpg", "width": "1280", "height": "720"},
{"index": "92", "name": "img (80).jpg", "width": "559", "height": "195"},
{"index": "93", "name": "img (81).jpg", "width": "326", "height": "397"},
{"index": "94", "name": "img (82).jpg", "width": "305", "height": "179"},
{"index": "95", "name": "img (83).jpg", "width": "457", "height": "455"},
{"index": "96", "name": "img (84).jpg", "width": "272", "height": "138"},
{"index": "97", "name": "img (85).jpg", "width": "360", "height": "239"},
{"index": "98", "name": "img (86).jpg", "width": "440", "height": "248"},
{"index": "99", "name": "img (87).jpg", "width": "580", "height": "171"},
{"index": "100", "name": "img (88).jpg", "width": "442", "height": "124"},
{"index": "101", "name": "img (89).jpg", "width": "219", "height": "179"},
{"index": "102", "name": "img (9).jpg", "width": "1280", "height": "720"},
{"index": "103", "name": "img (90).jpg", "width": "150", "height": "150"},
{"index": "104", "name": "img (91).jpg", "width": "200", "height": "174"},
{"index": "105", "name": "img (92).jpg", "width": "112", "height": "90"},
{"index": "106", "name": "img (93).jpg", "width": "133", "height": "143"},
{"index": "107", "name": "img (94).jpg", "width": "165", "height": "220"},
{"index": "108", "name": "img (95).jpg", "width": "80", "height": "106"},
{"index": "109", "name": "img (96).jpg", "width": "118", "height": "101"},
{"index": "110", "name": "img (97).jpg", "width": "210", "height": "33"},
{"index": "111", "name": "img (98).jpg", "width": "1500", "height": "912"},
{"index": "112", "name": "img (99).jpg", "width": "560", "height": "715"},
{"index": "113", "name": "t0109a95543ca518559.jpg", "width": "1280", "height": "800"}
]}